pyqt_description_tooltip/__init__.py
pyqt_description_tooltip/descriptionToolTipGetter.py
pyqt_description_tooltip-0.0.1.dist-info/LICENSE
pyqt_description_tooltip-0.0.1.dist-info/METADATA
pyqt_description_tooltip-0.0.1.dist-info/WHEEL
pyqt_description_tooltip-0.0.1.dist-info/top_level.txt
pyqt_description_tooltip-0.0.1.dist-info/RECORD
