Metadata-Version: 2.1
Name: pyqt-description-tooltip
Version: 0.0.1
Summary: PyQt QToolTip that user can add description and so on.
Home-page: https://github.com/yjg30737/pyqt-description-tooltip.git
Author: Jung Gyu Yoon
Author-email: yjg30737@gmail.com
License: MIT
Platform: UNKNOWN
License-File: LICENSE
